{
    "logo": {
        "altText": "Logo dark",
        "styles": {
            "self": {
                "margin": [
                    "mr-3"
                ]
            }
        },
        "type": "ImageBlock",
        "url": "/images/idamcyber.png"
    },
    "primaryLinks": [
        {
            "label": "Pricing",
            "url": "/",
            "icon": "arrowRight",
            "iconPosition": "right",
            "style": "secondary",
            "type": "Link"
        },
        {
            "label": "Certifications",
            "altText": "Certifications",
            "url": "/Certifications",
            "icon": "arrowRight",
            "iconPosition": "right",
            "style": "secondary",
            "type": "Link"
        },
        {
            "label": "Careers",
            "altText": "Careers page",
            "url": "/careers",
            "icon": "arrowRight",
            "iconPosition": "right",
            "style": "secondary",
            "type": "Link"
        },
        {
            "label": "Tech Support",
            "altText": "Tech Support",
            "links": [
                {
                    "label": "Assignments",
                    "url": "/",
                    "icon": "arrowRight",
                    "iconPosition": "right",
                    "style": "secondary",
                    "type": "Link"
                },
                {
                    "label": "Cloud Projects",
                    "url": "/",
                    "icon": "arrowRight",
                    "iconPosition": "right",
                    "style": "secondary",
                    "type": "Link"
                },
                {
                    "label": "Interview Support",
                    "url": "/",
                    "icon": "arrowRight",
                    "iconPosition": "right",
                    "style": "secondary",
                    "type": "Link"
                }
            ],
            "labelStyle": "secondary",
            "type": "SubNav"
        }
    ],
    "secondaryLinks": [
        {
            "label": "Sign up",
            "altText": "Sign up",
            "url": "https://app.netlify.com/signup",
            "icon": "arrowRight",
            "iconPosition": "right",
            "style": "secondary",
            "type": "Button"
        },
        {
            "label": "Log in",
            "url": "/",
            "icon": "arrowRight",
            "iconPosition": "right",
            "style": "primary",
            "type": "Button"
        }
    ],
    "variant": "logo-left-primary-nav-centered",
    "colors": "bg-light-fg-dark",
    "type": "Header"
}